<?xml version="1.0" encoding="utf-8"?><dataroot>
	<item>
		<autoId>1962</autoId>
		<languageId>5</languageId>
		<languageCh></languageCh>
		<dialectId>16</dialectId>
		<dialectCh></dialectCh>
		<typeId>4</typeId>
		<typeCh></typeCh>
		<classId>30</classId>
		<classCh>是非問句(問動作進行、能力、喜好--連動結構) </classCh>
		<classNo>5</classNo>
		<choiceOneOrder>1</choiceOneOrder>
		<choiceOneAAb>Waga su muuyas ka isu?</choiceOneAAb>
		<choiceOneACh>你在讀書嗎？</choiceOneACh>
		<choiceOneBAb>Un, ni ku muuya ka yaku.</choiceOneBAb>
		<choiceOneBCh>是的，我在讀書。</choiceOneBCh>
		<choiceOneCAb></choiceOneCAb>
		<choiceOneCCh></choiceOneCCh>
	</item>
	<item>
		<autoId>1961</autoId>
		<languageId>5</languageId>
		<languageCh></languageCh>
		<dialectId>16</dialectId>
		<dialectCh></dialectCh>
		<typeId>4</typeId>
		<typeCh></typeCh>
		<classId>30</classId>
		<classCh>是非問句(問動作進行、能力、喜好--連動結構) </classCh>
		<classNo>5</classNo>
		<choiceOneOrder>2</choiceOneOrder>
		<choiceOneAAb>Waga su muuyas ka isu?</choiceOneAAb>
		<choiceOneACh>你在讀書嗎？</choiceOneACh>
		<choiceOneBAb>Uxe, ni ku jiyuga ka yaku.</choiceOneBAb>
		<choiceOneBCh>不，我在畫畫。</choiceOneBCh>
		<choiceOneCAb></choiceOneCAb>
		<choiceOneCCh></choiceOneCCh>
	</item>
	<item>
		<autoId>1960</autoId>
		<languageId>5</languageId>
		<languageCh></languageCh>
		<dialectId>16</dialectId>
		<dialectCh></dialectCh>
		<typeId>4</typeId>
		<typeCh></typeCh>
		<classId>30</classId>
		<classCh>是非問句(問動作進行、能力、喜好--連動結構) </classCh>
		<classNo>5</classNo>
		<choiceOneOrder>3</choiceOneOrder>
		<choiceOneAAb>Waga mtaqi ka swai su mqedil?</choiceOneAAb>
		<choiceOneACh>你妹妹在睡覺嗎？</choiceOneACh>
		<choiceOneBAb>Un, waga mtaqi ka heya.</choiceOneBAb>
		<choiceOneBCh>是的，她在睡覺。</choiceOneBCh>
		<choiceOneCAb></choiceOneCAb>
		<choiceOneCCh></choiceOneCCh>
	</item>
	<item>
		<autoId>1959</autoId>
		<languageId>5</languageId>
		<languageCh></languageCh>
		<dialectId>16</dialectId>
		<dialectCh></dialectCh>
		<typeId>4</typeId>
		<typeCh></typeCh>
		<classId>30</classId>
		<classCh>是非問句(問動作進行、能力、喜好--連動結構) </classCh>
		<classNo>5</classNo>
		<choiceOneOrder>4</choiceOneOrder>
		<choiceOneAAb>Waga mtaqi ka swai su mqedil?</choiceOneAAb>
		<choiceOneACh>你妹妹在睡覺嗎？</choiceOneACh>
		<choiceOneBAb>Ini, ga kmeeki ka heya.</choiceOneBAb>
		<choiceOneBCh>不是，她在跳舞。</choiceOneBCh>
		<choiceOneCAb></choiceOneCAb>
		<choiceOneCCh></choiceOneCCh>
	</item>
	<item>
		<autoId>1958</autoId>
		<languageId>5</languageId>
		<languageCh></languageCh>
		<dialectId>16</dialectId>
		<dialectCh></dialectCh>
		<typeId>4</typeId>
		<typeCh></typeCh>
		<classId>30</classId>
		<classCh>是非問句(問動作進行、能力、喜好--連動結構) </classCh>
		<classNo>5</classNo>
		<choiceOneOrder>5</choiceOneOrder>
		<choiceOneAAb>Waga mtheyaq ka lqlaqi gaga?</choiceOneAAb>
		<choiceOneACh>那些孩子在玩耍嗎？</choiceOneACh>
		<choiceOneBAb>Un, waga mtheyaq ka lqlaqi gaga.</choiceOneBAb>
		<choiceOneBCh>是/對，那些孩子在玩耍。</choiceOneBCh>
		<choiceOneCAb></choiceOneCAb>
		<choiceOneCCh></choiceOneCCh>
	</item>
	<item>
		<autoId>1957</autoId>
		<languageId>5</languageId>
		<languageCh></languageCh>
		<dialectId>16</dialectId>
		<dialectCh></dialectCh>
		<typeId>4</typeId>
		<typeCh></typeCh>
		<classId>30</classId>
		<classCh>是非問句(問動作進行、能力、喜好--連動結構) </classCh>
		<classNo>5</classNo>
		<choiceOneOrder>6</choiceOneOrder>
		<choiceOneAAb>Waga muuyas uyas ka dheya ?</choiceOneAAb>
		<choiceOneACh>他們在唱歌嗎？</choiceOneACh>
		<choiceOneBAb>Uxe, waga muuyas ka dheya.</choiceOneBAb>
		<choiceOneBCh>不是，他們在讀書。</choiceOneBCh>
		<choiceOneCAb></choiceOneCAb>
		<choiceOneCCh></choiceOneCCh>
	</item>
	<item>
		<autoId>1956</autoId>
		<languageId>5</languageId>
		<languageCh></languageCh>
		<dialectId>16</dialectId>
		<dialectCh></dialectCh>
		<typeId>4</typeId>
		<typeCh></typeCh>
		<classId>30</classId>
		<classCh>是非問句(問動作進行、能力、喜好--連動結構) </classCh>
		<classNo>5</classNo>
		<choiceOneOrder>7</choiceOneOrder>
		<choiceOneAAb>Ga qmuyux?</choiceOneAAb>
		<choiceOneACh>在下雨嗎？</choiceOneACh>
		<choiceOneBAb>Un, ga qmuyux.</choiceOneBAb>
		<choiceOneBCh>是/對，正在下雨。</choiceOneBCh>
		<choiceOneCAb></choiceOneCAb>
		<choiceOneCCh></choiceOneCCh>
	</item>
	<item>
		<autoId>1955</autoId>
		<languageId>5</languageId>
		<languageCh></languageCh>
		<dialectId>16</dialectId>
		<dialectCh></dialectCh>
		<typeId>4</typeId>
		<typeCh></typeCh>
		<classId>30</classId>
		<classCh>是非問句(問動作進行、能力、喜好--連動結構) </classCh>
		<classNo>5</classNo>
		<choiceOneOrder>8</choiceOneOrder>
		<choiceOneAAb>Ga qmuyux?</choiceOneAAb>
		<choiceOneACh>在下雨嗎？</choiceOneACh>
		<choiceOneBAb>Ini, thido di!</choiceOneBAb>
		<choiceOneBCh>不，太陽出來了！</choiceOneBCh>
		<choiceOneCAb></choiceOneCAb>
		<choiceOneCCh></choiceOneCCh>
	</item>
	<item>
		<autoId>1954</autoId>
		<languageId>5</languageId>
		<languageCh></languageCh>
		<dialectId>16</dialectId>
		<dialectCh></dialectCh>
		<typeId>4</typeId>
		<typeCh></typeCh>
		<classId>30</classId>
		<classCh>是非問句(問動作進行、能力、喜好--連動結構) </classCh>
		<classNo>5</classNo>
		<choiceOneOrder>9</choiceOneOrder>
		<choiceOneAAb>Musa namu qmita tama rudan klaali ka yamu?</choiceOneAAb>
		<choiceOneACh>你們常常去探望祖父嗎？</choiceOneACh>
		<choiceOneBAb>Un, musa miyan qmita tama rudan klaali ka yami.</choiceOneBAb>
		<choiceOneBCh>對，我們常常去探望祖父。</choiceOneBCh>
		<choiceOneCAb></choiceOneCAb>
		<choiceOneCCh></choiceOneCCh>
	</item>
	<item>
		<autoId>1953</autoId>
		<languageId>5</languageId>
		<languageCh></languageCh>
		<dialectId>16</dialectId>
		<dialectCh></dialectCh>
		<typeId>4</typeId>
		<typeCh></typeCh>
		<classId>30</classId>
		<classCh>是非問句(問動作進行、能力、喜好--連動結構) </classCh>
		<classNo>5</classNo>
		<choiceOneOrder>10</choiceOneOrder>
		<choiceOneAAb>Mkela su mahu lukus ka isu?</choiceOneAAb>
		<choiceOneACh>你會洗衣服嗎？</choiceOneACh>
		<choiceOneBAb>Un, mkela ku mahu lukus ka yaku.</choiceOneBAb>
		<choiceOneBCh>會，我會洗衣服。</choiceOneBCh>
		<choiceOneCAb></choiceOneCAb>
		<choiceOneCCh></choiceOneCCh>
	</item>
	<item>
		<autoId>1952</autoId>
		<languageId>5</languageId>
		<languageCh></languageCh>
		<dialectId>16</dialectId>
		<dialectCh></dialectCh>
		<typeId>4</typeId>
		<typeCh></typeCh>
		<classId>30</classId>
		<classCh>是非問句(問動作進行、能力、喜好--連動結構) </classCh>
		<classNo>5</classNo>
		<choiceOneOrder>11</choiceOneOrder>
		<choiceOneAAb>Mkela muuyas uyas ka lqlaqi gaga?</choiceOneAAb>
		<choiceOneACh>那些孩子會唱歌嗎？</choiceOneACh>
		<choiceOneBAb>Un, mkela muuyas uyas ka lqlaqi gaga.</choiceOneBAb>
		<choiceOneBCh>是，他們很會唱歌。</choiceOneBCh>
		<choiceOneCAb></choiceOneCAb>
		<choiceOneCCh></choiceOneCCh>
	</item>
	<item>
		<autoId>1951</autoId>
		<languageId>5</languageId>
		<languageCh></languageCh>
		<dialectId>16</dialectId>
		<dialectCh></dialectCh>
		<typeId>4</typeId>
		<typeCh></typeCh>
		<classId>30</classId>
		<classCh>是非問句(問動作進行、能力、喜好--連動結構) </classCh>
		<classNo>5</classNo>
		<choiceOneOrder>12</choiceOneOrder>
		<choiceOneAAb>Smkuxul su muuyas ka isu?</choiceOneAAb>
		<choiceOneACh>你喜歡讀書嗎？</choiceOneACh>
		<choiceOneBAb>Un, smkuxul ku muuyas ka yaku?</choiceOneBAb>
		<choiceOneBCh>是/對，我喜歡讀書。</choiceOneBCh>
		<choiceOneCAb></choiceOneCAb>
		<choiceOneCCh></choiceOneCCh>
	</item>
	<item>
		<autoId>1950</autoId>
		<languageId>5</languageId>
		<languageCh></languageCh>
		<dialectId>16</dialectId>
		<dialectCh></dialectCh>
		<typeId>4</typeId>
		<typeCh></typeCh>
		<classId>30</classId>
		<classCh>是非問句(問動作進行、能力、喜好--連動結構) </classCh>
		<classNo>5</classNo>
		<choiceOneOrder>13</choiceOneOrder>
		<choiceOneAAb>Smkuxul jiyuga ka laqi gaga?</choiceOneAAb>
		<choiceOneACh>那個孩子喜歡畫圖嗎？</choiceOneACh>
		<choiceOneBAb>Un, smkuxul jiyuga ka laqi gaga.</choiceOneBAb>
		<choiceOneBCh>是/對，他很喜歡畫圖。</choiceOneBCh>
		<choiceOneCAb></choiceOneCAb>
		<choiceOneCCh></choiceOneCCh>
	</item>
	<item>
		<autoId>1949</autoId>
		<languageId>5</languageId>
		<languageCh></languageCh>
		<dialectId>16</dialectId>
		<dialectCh></dialectCh>
		<typeId>4</typeId>
		<typeCh></typeCh>
		<classId>30</classId>
		<classCh>是非問句(問動作進行、能力、喜好--連動結構) </classCh>
		<classNo>5</classNo>
		<choiceOneOrder>14</choiceOneOrder>
		<choiceOneAAb>Smkuxul muuyas uyas ka lqlaqi gaga?</choiceOneAAb>
		<choiceOneACh>那些孩子喜歡唱歌嗎？</choiceOneACh>
		<choiceOneBAb>Un. smkuxul muuyas uyas ka dheya.</choiceOneBAb>
		<choiceOneBCh>是，他們喜歡唱歌。</choiceOneBCh>
		<choiceOneCAb></choiceOneCAb>
		<choiceOneCCh></choiceOneCCh>
	</item>
	<item>
		<autoId>1948</autoId>
		<languageId>5</languageId>
		<languageCh></languageCh>
		<dialectId>16</dialectId>
		<dialectCh></dialectCh>
		<typeId>4</typeId>
		<typeCh></typeCh>
		<classId>30</classId>
		<classCh>是非問句(問動作進行、能力、喜好--連動結構) </classCh>
		<classNo>5</classNo>
		<choiceOneOrder>15</choiceOneOrder>
		<choiceOneAAb>Smkuxul kmeeki ka lqlaqi gaga ?</choiceOneAAb>
		<choiceOneACh>那些孩子喜歡跳舞嗎？</choiceOneACh>
		<choiceOneBAb>Ini, smkuxul qmita terebi ka dheya.</choiceOneBAb>
		<choiceOneBCh>不，他們喜歡看電視。</choiceOneBCh>
		<choiceOneCAb></choiceOneCAb>
		<choiceOneCCh></choiceOneCCh>
	</item>
	<item>
		<autoId>1947</autoId>
		<languageId>5</languageId>
		<languageCh></languageCh>
		<dialectId>16</dialectId>
		<dialectCh></dialectCh>
		<typeId>4</typeId>
		<typeCh></typeCh>
		<classId>30</classId>
		<classCh>是非問句(問動作進行、能力、喜好--連動結構) </classCh>
		<classNo>5</classNo>
		<choiceOneOrder>16</choiceOneOrder>
		<choiceOneAAb>Smkuxul mtheyaq ka lqlaqi gaga?</choiceOneAAb>
		<choiceOneACh>那些孩子喜歡玩耍嗎？</choiceOneACh>
		<choiceOneBAb>Ini, smkuxul mekan ka dheya.</choiceOneBAb>
		<choiceOneBCh>不，他們喜歡吃東西。</choiceOneBCh>
		<choiceOneCAb></choiceOneCAb>
		<choiceOneCCh></choiceOneCCh>
	</item>
</dataroot>