<?xml version="1.0" encoding="utf-8"?><dataroot>
	<item>
		<autoId>24711</autoId>
		<languageId>2</languageId>
		<languageCh></languageCh>
		<dialectId>9</dialectId>
		<dialectCh></dialectCh>
		<typeId>1</typeId>
		<typeCh></typeCh>
		<classId>4</classId>
		<classCh>親屬</classCh>
		<classNo>4</classNo>
		<wordOrder>1</wordOrder>
		<wordAb>yaba'</wordAb>
		<wordCh>爸爸</wordCh>
	</item>
	<item>
		<autoId>24712</autoId>
		<languageId>2</languageId>
		<languageCh></languageCh>
		<dialectId>9</dialectId>
		<dialectCh></dialectCh>
		<typeId>1</typeId>
		<typeCh></typeCh>
		<classId>4</classId>
		<classCh>親屬</classCh>
		<classNo>4</classNo>
		<wordOrder>2</wordOrder>
		<wordAb>yaya'</wordAb>
		<wordCh>媽媽</wordCh>
	</item>
	<item>
		<autoId>24713</autoId>
		<languageId>2</languageId>
		<languageCh></languageCh>
		<dialectId>9</dialectId>
		<dialectCh></dialectCh>
		<typeId>1</typeId>
		<typeCh></typeCh>
		<classId>4</classId>
		<classCh>親屬</classCh>
		<classNo>4</classNo>
		<wordOrder>3</wordOrder>
		<wordAb>yutas</wordAb>
		<wordCh>祖父</wordCh>
	</item>
	<item>
		<autoId>24714</autoId>
		<languageId>2</languageId>
		<languageCh></languageCh>
		<dialectId>9</dialectId>
		<dialectCh></dialectCh>
		<typeId>1</typeId>
		<typeCh></typeCh>
		<classId>4</classId>
		<classCh>親屬</classCh>
		<classNo>4</classNo>
		<wordOrder>4</wordOrder>
		<wordAb>yaki'</wordAb>
		<wordCh>祖母</wordCh>
	</item>
	<item>
		<autoId>24715</autoId>
		<languageId>2</languageId>
		<languageCh></languageCh>
		<dialectId>9</dialectId>
		<dialectCh></dialectCh>
		<typeId>1</typeId>
		<typeCh></typeCh>
		<classId>4</classId>
		<classCh>親屬</classCh>
		<classNo>4</classNo>
		<wordOrder>5</wordOrder>
		<wordAb>asuṟan </wordAb>
		<wordCh>哥；姊</wordCh>
	</item>
	<item>
		<autoId>24716</autoId>
		<languageId>2</languageId>
		<languageCh></languageCh>
		<dialectId>9</dialectId>
		<dialectCh></dialectCh>
		<typeId>1</typeId>
		<typeCh></typeCh>
		<classId>4</classId>
		<classCh>親屬</classCh>
		<classNo>4</classNo>
		<wordOrder>6</wordOrder>
		<wordAb>asuṟan  malikuṟ</wordAb>
		<wordCh>哥哥</wordCh>
	</item>
	<item>
		<autoId>24717</autoId>
		<languageId>2</languageId>
		<languageCh></languageCh>
		<dialectId>9</dialectId>
		<dialectCh></dialectCh>
		<typeId>1</typeId>
		<typeCh></typeCh>
		<classId>4</classId>
		<classCh>親屬</classCh>
		<classNo>4</classNo>
		<wordOrder>7</wordOrder>
		<wordAb>asuṟan  kanel</wordAb>
		<wordCh>姊姊</wordCh>
	</item>
	<item>
		<autoId>24719</autoId>
		<languageId>2</languageId>
		<languageCh></languageCh>
		<dialectId>9</dialectId>
		<dialectCh></dialectCh>
		<typeId>1</typeId>
		<typeCh></typeCh>
		<classId>4</classId>
		<classCh>親屬</classCh>
		<classNo>4</classNo>
		<wordOrder>8</wordOrder>
		<wordAb>suse'</wordAb>
		<wordCh>弟；妹</wordCh>
	</item>
	<item>
		<autoId>24718</autoId>
		<languageId>2</languageId>
		<languageCh></languageCh>
		<dialectId>9</dialectId>
		<dialectCh></dialectCh>
		<typeId>1</typeId>
		<typeCh></typeCh>
		<classId>4</classId>
		<classCh>親屬</classCh>
		<classNo>4</classNo>
		<wordOrder>9</wordOrder>
		<wordAb>suse'  malikuṟ</wordAb>
		<wordCh>弟弟</wordCh>
	</item>
	<item>
		<autoId>24720</autoId>
		<languageId>2</languageId>
		<languageCh></languageCh>
		<dialectId>9</dialectId>
		<dialectCh></dialectCh>
		<typeId>1</typeId>
		<typeCh></typeCh>
		<classId>4</classId>
		<classCh>親屬</classCh>
		<classNo>4</classNo>
		<wordOrder>10</wordOrder>
		<wordAb>suse'  kanel</wordAb>
		<wordCh>妹妹</wordCh>
	</item>
	<item>
		<autoId>24721</autoId>
		<languageId>2</languageId>
		<languageCh></languageCh>
		<dialectId>9</dialectId>
		<dialectCh></dialectCh>
		<typeId>1</typeId>
		<typeCh></typeCh>
		<classId>4</classId>
		<classCh>親屬</classCh>
		<classNo>4</classNo>
		<wordOrder>11</wordOrder>
		<wordAb>macsuse'</wordAb>
		<wordCh>兄弟姊妹</wordCh>
	</item>
	<item>
		<autoId>24722</autoId>
		<languageId>2</languageId>
		<languageCh></languageCh>
		<dialectId>9</dialectId>
		<dialectCh></dialectCh>
		<typeId>1</typeId>
		<typeCh></typeCh>
		<classId>4</classId>
		<classCh>親屬</classCh>
		<classNo>4</classNo>
		<wordOrder>12</wordOrder>
		<wordAb>mama'</wordAb>
		<wordCh>伯父；叔叔；舅舅</wordCh>
	</item>
</dataroot>