<?xml version="1.0" encoding="utf-8"?><dataroot>
	<item>
		<autoId>3795</autoId>
		<languageId>12</languageId>
		<languageCh></languageCh>
		<dialectId>39</dialectId>
		<dialectCh></dialectCh>
		<typeId>4</typeId>
		<typeCh></typeCh>
		<classId>29</classId>
		<classCh>是非問句(問職業、關係、數量、物品、健康、外貌、動作、天氣)</classCh>
		<classNo>4</classNo>
		<choiceOneOrder>1</choiceOneOrder>
		<choiceOneAAb>a temakakesi u?</choiceOneAAb>
		<choiceOneACh>你是學生嗎？</choiceOneACh>
		<choiceOneBAb>ai, a temakakesi ku.</choiceOneBAb>
		<choiceOneBCh>是，我是學生。</choiceOneBCh>
		<choiceOneCAb></choiceOneCAb>
		<choiceOneCCh></choiceOneCCh>
	</item>
	<item>
		<autoId>3794</autoId>
		<languageId>12</languageId>
		<languageCh></languageCh>
		<dialectId>39</dialectId>
		<dialectCh></dialectCh>
		<typeId>4</typeId>
		<typeCh></typeCh>
		<classId>29</classId>
		<classCh>是非問句(問職業、關係、數量、物品、健康、外貌、動作、天氣)</classCh>
		<classNo>4</classNo>
		<choiceOneOrder>2</choiceOneOrder>
		<choiceOneAAb>a sinsi intaw?</choiceOneAAb>
		<choiceOneACh>他是老師嗎？</choiceOneACh>
		<choiceOneBAb>melri, i intaw mu maw na ising.</choiceOneBAb>
		<choiceOneBCh>不是，他是醫生。</choiceOneBCh>
		<choiceOneCAb></choiceOneCAb>
		<choiceOneCCh></choiceOneCCh>
	</item>
	<item>
		<autoId>3793</autoId>
		<languageId>12</languageId>
		<languageCh></languageCh>
		<dialectId>39</dialectId>
		<dialectCh></dialectCh>
		<typeId>4</typeId>
		<typeCh></typeCh>
		<classId>29</classId>
		<classCh>是非問句(問職業、關係、數量、物品、健康、外貌、動作、天氣)</classCh>
		<classNo>4</classNo>
		<choiceOneOrder>3</choiceOneOrder>
		<choiceOneAAb>ninnu sinsi i intaw?</choiceOneAAb>
		<choiceOneACh>他是你的老師嗎？</choiceOneACh>
		<choiceOneBAb>ai, i intaw mu maw nanku sinsi. /ai, maw nanku sinsi i intaw.</choiceOneBAb>
		<choiceOneBCh>是/對，他是我的老師。</choiceOneBCh>
		<choiceOneCAb></choiceOneCAb>
		<choiceOneCCh></choiceOneCCh>
	</item>
	<item>
		<autoId>3792</autoId>
		<languageId>12</languageId>
		<languageCh></languageCh>
		<dialectId>39</dialectId>
		<dialectCh></dialectCh>
		<typeId>4</typeId>
		<typeCh></typeCh>
		<classId>29</classId>
		<classCh>是非問句(問職業、關係、數量、物品、健康、外貌、動作、天氣)</classCh>
		<classNo>4</classNo>
		<choiceOneOrder>4</choiceOneOrder>
		<choiceOneAAb>intaw mu maw tu maralrak ni temama?</choiceOneAAb>
		<choiceOneACh>他是你的叔叔嗎？</choiceOneACh>
		<choiceOneBAb>melri, i intaw mu maw nanku sinsi.</choiceOneBAb>
		<choiceOneBCh>不是，他是我的老師。</choiceOneBCh>
		<choiceOneCAb></choiceOneCAb>
		<choiceOneCCh></choiceOneCCh>
	</item>
	<item>
		<autoId>3791</autoId>
		<languageId>12</languageId>
		<languageCh></languageCh>
		<dialectId>39</dialectId>
		<dialectCh></dialectCh>
		<typeId>4</typeId>
		<typeCh></typeCh>
		<classId>29</classId>
		<classCh>是非問句(問職業、關係、數量、物品、健康、外貌、動作、天氣)</classCh>
		<classNo>4</classNo>
		<choiceOneOrder>5</choiceOneOrder>
		<choiceOneAAb>ulra sasa nu wadi a vavayan?</choiceOneAAb>
		<choiceOneACh>你有一個妹妹嗎？</choiceOneACh>
		<choiceOneBAb>'azi,  zazuwa ku wadi na vavayan.</choiceOneBAb>
		<choiceOneBCh>不，我有二個妹妹。</choiceOneBCh>
		<choiceOneCAb></choiceOneCAb>
		<choiceOneCCh></choiceOneCCh>
	</item>
	<item>
		<autoId>3790</autoId>
		<languageId>12</languageId>
		<languageCh></languageCh>
		<dialectId>39</dialectId>
		<dialectCh></dialectCh>
		<typeId>4</typeId>
		<typeCh></typeCh>
		<classId>29</classId>
		<classCh>是非問句(問職業、關係、數量、物品、健康、外貌、動作、天氣)</classCh>
		<classNo>4</classNo>
		<choiceOneOrder>6</choiceOneOrder>
		<choiceOneAAb>ulra zazuwa i wadiyu na ma'inay?</choiceOneAAb>
		<choiceOneACh>你有兩個弟弟嗎？</choiceOneACh>
		<choiceOneBAb>'azi, ulra i valri na ma'inay a sasa zi wadilri na ma'inay  a sasa.</choiceOneBAb>
		<choiceOneBCh>不，我有一個哥哥一個弟弟。</choiceOneBCh>
		<choiceOneCAb></choiceOneCAb>
		<choiceOneCCh></choiceOneCCh>
	</item>
	<item>
		<autoId>3789</autoId>
		<languageId>12</languageId>
		<languageCh></languageCh>
		<dialectId>39</dialectId>
		<dialectCh></dialectCh>
		<typeId>4</typeId>
		<typeCh></typeCh>
		<classId>29</classId>
		<classCh>是非問句(問職業、關係、數量、物品、健康、外貌、動作、天氣)</classCh>
		<classNo>4</classNo>
		<choiceOneOrder>7</choiceOneOrder>
		<choiceOneAAb>ulra zazuwa i vau na vavayan?</choiceOneAAb>
		<choiceOneACh>你有兩個姊姊嗎？</choiceOneACh>
		<choiceOneBAb>'azi, sasa i valri na vavayan zi sasa i valri na ma'inay.</choiceOneBAb>
		<choiceOneBCh>不，我有一個姊姊一個哥哥。</choiceOneBCh>
		<choiceOneCAb></choiceOneCAb>
		<choiceOneCCh></choiceOneCCh>
	</item>
	<item>
		<autoId>3788</autoId>
		<languageId>12</languageId>
		<languageCh></languageCh>
		<dialectId>39</dialectId>
		<dialectCh></dialectCh>
		<typeId>4</typeId>
		<typeCh></typeCh>
		<classId>29</classId>
		<classCh>是非問句(問職業、關係、數量、物品、健康、外貌、動作、天氣)</classCh>
		<classNo>4</classNo>
		<choiceOneOrder>8</choiceOneOrder>
		<choiceOneAAb>maw naku paysu i ini?</choiceOneAAb>
		<choiceOneACh>這是我的錢嗎？</choiceOneACh>
		<choiceOneBAb>ai, ninnu paysu i ini.</choiceOneBAb>
		<choiceOneBCh>是的，這是你的錢。</choiceOneBCh>
		<choiceOneCAb></choiceOneCAb>
		<choiceOneCCh></choiceOneCCh>
	</item>
	<item>
		<autoId>3787</autoId>
		<languageId>12</languageId>
		<languageCh></languageCh>
		<dialectId>39</dialectId>
		<dialectCh></dialectCh>
		<typeId>4</typeId>
		<typeCh></typeCh>
		<classId>29</classId>
		<classCh>是非問句(問職業、關係、數量、物品、健康、外貌、動作、天氣)</classCh>
		<classNo>4</classNo>
		<choiceOneOrder>9</choiceOneOrder>
		<choiceOneAAb>maw ninnu 'aputr naziyu?</choiceOneAAb>
		<choiceOneACh>那些是你的花嗎？</choiceOneACh>
		<choiceOneBAb>melri, melri naku 'aputr nazu.</choiceOneBAb>
		<choiceOneBCh>不是，那些不是我的花。</choiceOneBCh>
		<choiceOneCAb></choiceOneCAb>
		<choiceOneCCh></choiceOneCCh>
	</item>
	<item>
		<autoId>3786</autoId>
		<languageId>12</languageId>
		<languageCh></languageCh>
		<dialectId>39</dialectId>
		<dialectCh></dialectCh>
		<typeId>4</typeId>
		<typeCh></typeCh>
		<classId>29</classId>
		<classCh>是非問句(問職業、關係、數量、物品、健康、外貌、動作、天氣)</classCh>
		<classNo>4</classNo>
		<choiceOneOrder>10</choiceOneOrder>
		<choiceOneAAb>'inava u ziya?</choiceOneAAb>
		<choiceOneACh>你怎麼了？</choiceOneACh>
		<choiceOneBAb>salaw nana ku tranguru'.</choiceOneBAb>
		<choiceOneBCh>我的頭很痛。</choiceOneBCh>
		<choiceOneCAb></choiceOneCAb>
		<choiceOneCCh></choiceOneCCh>
	</item>
	<item>
		<autoId>3785</autoId>
		<languageId>12</languageId>
		<languageCh></languageCh>
		<dialectId>39</dialectId>
		<dialectCh></dialectCh>
		<typeId>4</typeId>
		<typeCh></typeCh>
		<classId>29</classId>
		<classCh>是非問句(問職業、關係、數量、物品、健康、外貌、動作、天氣)</classCh>
		<classNo>4</classNo>
		<choiceOneOrder>11</choiceOneOrder>
		<choiceOneAAb>'inava u ziya?</choiceOneAAb>
		<choiceOneACh>你怎麼了？</choiceOneACh>
		<choiceOneBAb>salaw nana ku matra.</choiceOneBAb>
		<choiceOneBCh>我的眼睛很痛。</choiceOneBCh>
		<choiceOneCAb></choiceOneCAb>
		<choiceOneCCh></choiceOneCCh>
	</item>
	<item>
		<autoId>3784</autoId>
		<languageId>12</languageId>
		<languageCh></languageCh>
		<dialectId>39</dialectId>
		<dialectCh></dialectCh>
		<typeId>4</typeId>
		<typeCh></typeCh>
		<classId>29</classId>
		<classCh>是非問句(問職業、關係、數量、物品、健康、外貌、動作、天氣)</classCh>
		<classNo>4</classNo>
		<choiceOneOrder>12</choiceOneOrder>
		<choiceOneAAb>'aluzun ini na to?</choiceOneAAb>
		<choiceOneACh>這張桌子很重嗎？</choiceOneACh>
		<choiceOneBAb>ai, salaw 'aluzun ini na to.</choiceOneBAb>
		<choiceOneBCh>是/對，這張桌子很重。</choiceOneBCh>
		<choiceOneCAb></choiceOneCAb>
		<choiceOneCCh></choiceOneCCh>
	</item>
	<item>
		<autoId>3783</autoId>
		<languageId>12</languageId>
		<languageCh></languageCh>
		<dialectId>39</dialectId>
		<dialectCh></dialectCh>
		<typeId>4</typeId>
		<typeCh></typeCh>
		<classId>29</classId>
		<classCh>是非問句(問職業、關係、數量、物品、健康、外貌、動作、天氣)</classCh>
		<classNo>4</classNo>
		<choiceOneOrder>13</choiceOneOrder>
		<choiceOneAAb>'aluzun izu na lipad.</choiceOneAAb>
		<choiceOneACh>那張椅子很重嗎？</choiceOneACh>
		<choiceOneBAb>'azi, atra'alr izu na lipad.</choiceOneBAb>
		<choiceOneBCh>不，那張椅子很輕。</choiceOneBCh>
		<choiceOneCAb></choiceOneCAb>
		<choiceOneCCh></choiceOneCCh>
	</item>
	<item>
		<autoId>3782</autoId>
		<languageId>12</languageId>
		<languageCh></languageCh>
		<dialectId>39</dialectId>
		<dialectCh></dialectCh>
		<typeId>4</typeId>
		<typeCh></typeCh>
		<classId>29</classId>
		<classCh>是非問句(問職業、關係、數量、物品、健康、外貌、動作、天氣)</classCh>
		<classNo>4</classNo>
		<choiceOneOrder>14</choiceOneOrder>
		<choiceOneAAb>'uze'uzem nanu ngiyaw? / nanu ngaiyaw mu maw na 'uze'uzem?</choiceOneAAb>
		<choiceOneACh>你的貓是黑色的嗎？</choiceOneACh>
		<choiceOneBAb>ai, 'uze'uzem nanku ngiyaw.</choiceOneBAb>
		<choiceOneBCh>是/對，我的貓是黑色的。</choiceOneBCh>
		<choiceOneCAb></choiceOneCAb>
		<choiceOneCCh></choiceOneCCh>
	</item>
	<item>
		<autoId>3781</autoId>
		<languageId>12</languageId>
		<languageCh></languageCh>
		<dialectId>39</dialectId>
		<dialectCh></dialectCh>
		<typeId>4</typeId>
		<typeCh></typeCh>
		<classId>29</classId>
		<classCh>是非問句(問職業、關係、數量、物品、健康、外貌、動作、天氣)</classCh>
		<classNo>4</classNo>
		<choiceOneOrder>15</choiceOneOrder>
		<choiceOneAAb>menana'u za tilibi kana wariwari ziya nazu?</choiceOneAAb>
		<choiceOneACh>他們天天看電視嗎？</choiceOneACh>
		<choiceOneBAb>ai, kana wariwari ziya mu menana'u za tilibi nazu.</choiceOneBAb>
		<choiceOneBCh>是/對，他們天天看電視。</choiceOneBCh>
		<choiceOneCAb></choiceOneCAb>
		<choiceOneCCh></choiceOneCCh>
	</item>
	<item>
		<autoId>3780</autoId>
		<languageId>12</languageId>
		<languageCh></languageCh>
		<dialectId>39</dialectId>
		<dialectCh></dialectCh>
		<typeId>4</typeId>
		<typeCh></typeCh>
		<classId>29</classId>
		<classCh>是非問句(問職業、關係、數量、物品、健康、外貌、動作、天氣)</classCh>
		<classNo>4</classNo>
		<choiceOneOrder>16</choiceOneOrder>
		<choiceOneAAb>'inava na wari harem?</choiceOneAAb>
		<choiceOneACh>今天天氣好嗎？</choiceOneACh>
		<choiceOneBAb>ai, 'inava na wari harem.</choiceOneBAb>
		<choiceOneBCh>是/對，今天天氣很好。</choiceOneBCh>
		<choiceOneCAb></choiceOneCAb>
		<choiceOneCCh></choiceOneCCh>
	</item>
</dataroot>