<?xml version="1.0" encoding="utf-8"?><dataroot>
	<item>
		<autoId>1530</autoId>
		<languageId>4</languageId>
		<languageCh></languageCh>
		<dialectId>14</dialectId>
		<dialectCh></dialectCh>
		<typeId>5</typeId>
		<typeCh></typeCh>
		<classId>31</classId>
		<classCh>訊息問句[問姓名或關係]</classCh>
		<classNo>1</classNo>
		<choiceTwoOrder>1</choiceTwoOrder>
		<choiceTwoAAb>kuzan mihu a ama wa lhanaz?</choiceTwoAAb>
		<choiceTwoACh>你爸爸叫甚麼名字？</choiceTwoACh>
		<choiceTwoBAb>kuzan mihu a apura'in a lhanaz?</choiceTwoBAb>
		<choiceTwoBCh>你祖父叫甚麼名字？</choiceTwoBCh>
		<choiceTwoCAb>kuzan mihu a fuifuilh patashan a shinshii a lhanaz?</choiceTwoCAb>
		<choiceTwoCCh>你老師叫甚麼名字？</choiceTwoCCh>
	</item>
	<item>
		<autoId>1529</autoId>
		<languageId>4</languageId>
		<languageCh></languageCh>
		<dialectId>14</dialectId>
		<dialectCh></dialectCh>
		<typeId>5</typeId>
		<typeCh></typeCh>
		<classId>31</classId>
		<classCh>訊息問句[問姓名或關係]</classCh>
		<classNo>1</classNo>
		<choiceTwoOrder>2</choiceTwoOrder>
		<choiceTwoAAb>kuzan thithu a tantuqash binanau'az a lhanaz?</choiceTwoAAb>
		<choiceTwoACh>他姊姊叫甚麼名字？</choiceTwoACh>
		<choiceTwoBAb>kuzan thithu a apuki'ay a lhanaz?</choiceTwoBAb>
		<choiceTwoBCh>他祖母叫甚麼名字？</choiceTwoBCh>
		<choiceTwoCAb>kuzan thithu a ina wa lhanaz?</choiceTwoCAb>
		<choiceTwoCCh>他媽媽叫甚麼名字？</choiceTwoCCh>
	</item>
	<item>
		<autoId>1528</autoId>
		<languageId>4</languageId>
		<languageCh></languageCh>
		<dialectId>14</dialectId>
		<dialectCh></dialectCh>
		<typeId>5</typeId>
		<typeCh></typeCh>
		<classId>31</classId>
		<classCh>訊息問句[問姓名或關係]</classCh>
		<classNo>1</classNo>
		<choiceTwoOrder>3</choiceTwoOrder>
		<choiceTwoAAb>kuzan huya mriqariqaz shiz a shinshii a lhanaz?</choiceTwoAAb>
		<choiceTwoACh>那個醫生叫甚麼名字？</choiceTwoACh>
		<choiceTwoBAb>kuzan huya fuifuilh patashan a shinshii a lhanaz?</choiceTwoBAb>
		<choiceTwoBCh>那個老師叫甚麼名字？</choiceTwoBCh>
		<choiceTwoCAb>kuzan huya lhmupishuan a azazak a lhanaz?</choiceTwoCAb>
		<choiceTwoCCh>那個學生叫甚麼名字？</choiceTwoCCh>
	</item>
	<item>
		<autoId>1527</autoId>
		<languageId>4</languageId>
		<languageCh></languageCh>
		<dialectId>14</dialectId>
		<dialectCh></dialectCh>
		<typeId>5</typeId>
		<typeCh></typeCh>
		<classId>31</classId>
		<classCh>訊息問句[問姓名或關係]</classCh>
		<classNo>1</classNo>
		<choiceTwoOrder>4</choiceTwoOrder>
		<choiceTwoAAb>kuzan huya binanau'az a lhanaz?</choiceTwoAAb>
		<choiceTwoACh>那個女人叫甚麼名字？</choiceTwoACh>
		<choiceTwoBAb>kuzan huya ayuzi a lhanaz?</choiceTwoBAb>
		<choiceTwoBCh>那個男人叫甚麼名字？</choiceTwoBCh>
		<choiceTwoCAb>kuzan huya tanatuqash a lhanaz?</choiceTwoCAb>
		<choiceTwoCCh>那個老人叫甚麼名字？</choiceTwoCCh>
	</item>
	<item>
		<autoId>1526</autoId>
		<languageId>4</languageId>
		<languageCh></languageCh>
		<dialectId>14</dialectId>
		<dialectCh></dialectCh>
		<typeId>5</typeId>
		<typeCh></typeCh>
		<classId>31</classId>
		<classCh>訊息問句[問姓名或關係]</classCh>
		<classNo>1</classNo>
		<choiceTwoOrder>5</choiceTwoOrder>
		<choiceTwoAAb>tima s izui a tanatuqash?</choiceTwoAAb>
		<choiceTwoACh>那個老人是誰？</choiceTwoACh>
		<choiceTwoBAb>tima s izui a ayuzi?</choiceTwoBAb>
		<choiceTwoBCh>那個男人是誰？</choiceTwoBCh>
		<choiceTwoCAb>tima s izui a azazak?</choiceTwoCAb>
		<choiceTwoCCh>那個小孩是誰？</choiceTwoCCh>
	</item>
</dataroot>