<?xml version='1.0' encoding='utf-8'?><dataroot><title>kadjalanan</title><titleCh>馬路</titleCh><item><text>liav a ravac a zidusia i kadjalanan,</text><chinese>馬路上汽車很多</chinese><wordChinese>多的 虛詞 很 虛詞 汽車 虛詞 馬路</wordChinese><sound>true</sound><order>1</order></item><title>kadjalanan</title><titleCh>馬路</titleCh><item><text>kinemenem i then nu diemavadjavac i tjen .</text><chinese>我們走路要小心</chinese><wordChinese>小心 虛詞 我們（受格） 虛詞 走路 虛詞 走路 虛詞 我們（受格）</wordChinese><sound>true</sound><order>2</order></item><title>kadjalanan</title><titleCh>馬路</titleCh><item><text>nu maka basu i tjen, masasuitaita i tjen a ljevavav .</text><chinese>搭公車要依序上車</chinese><wordChinese>虛詞 乘 公車 虛詞 我們（受格） 依序 虛詞 我們（受格） 上車</wordChinese><sound>true</sound><order>3</order></item><title>kadjalanan</title><titleCh>馬路</titleCh><item><text>nu maka utubai i tjen, tjemalupung i tjen tua anzingmau .</text><chinese>騎機車一定要戴安全帽</chinese><wordChinese>虛詞 騎 機車 虛詞 我們（受格） 戴帽子 虛詞 我們（受格） 虛詞 安全帽</wordChinese><sound>true</sound><order>4</order></item></dataroot>
