<?xml version='1.0' encoding='utf-8'?><dataroot><title>ngyalribatenga ki mwalringedele</title><titleCh>下午</titleCh><item><text>lu ngilribatenga ki mwalringedele, lrimaka ngulatatadraaku?</text><chinese>今天下午我可以出去玩嗎？</chinese><wordChinese>如果 過了 虛詞 中午 可以 出去玩─我</wordChinese><sound>true</sound><order>1</order></item><title>ngyalribatenga ki mwalringedele</title><titleCh>下午</titleCh><item><text>ini, tarwadradrau ka udale latadre.</text><chinese>不行，外面下著大雨。</chinese><wordChinese>不是/不行 下很大 虛詞 雨 外面</wordChinese><sound>true</sound><order>2</order></item><title>ngyalribatenga ki mwalringedele</title><titleCh>下午</titleCh><item><text>ala ceeka, lai lrimaka ngulatatadraaku?</text><chinese>如果雨停了，我可以出去玩嗎？</chinese><wordChinese>如果 雨停 虛詞 能 出去玩--我</wordChinese><sound>true</sound><order>3</order></item><title>ngyalribatenga ki mwalringedele</title><titleCh>下午</titleCh><item><text>kailrikatumane, ai ngwalringau madu luka myauaubu si mutavanane.</text><chinese>可以，但是記得傍晚要回家喔！</chinese><wordChinese>可以 但是 記得 虛詞 虛詞 傍晚 虛詞 回家</wordChinese><sound>true</sound><order>4</order></item></dataroot>
