<?xml version="1.0" encoding="utf-8"?><dataroot>
	<item>
		<autoId>5073</autoId>
		<languageId>16</languageId>
		<languageCh></languageCh>
		<dialectId>37</dialectId>
		<dialectCh></dialectCh>
		<typeId>4</typeId>
		<typeCh></typeCh>
		<classId>30</classId>
		<classCh>單一動詞[氣象景觀]</classCh>
		<classNo>5</classNo>
		<choiceOneOrder>1</choiceOneOrder>
		<choiceOneAAb>murumita cua tahliariia!</choiceOneAAb>
		<choiceOneACh>太陽出來了！</choiceOneACh>
		<choiceOneBAb>murumita cua vulahlʉ!</choiceOneBAb>
		<choiceOneBCh>月亮出來了！</choiceOneBCh>
		<choiceOneCAb>murumita cua 'acangʉrahlʉ!</choiceOneCAb>
		<choiceOneCCh>星星出來了！</choiceOneCCh>
	</item>
	<item>
		<autoId>5072</autoId>
		<languageId>16</languageId>
		<languageCh></languageCh>
		<dialectId>37</dialectId>
		<dialectCh></dialectCh>
		<typeId>4</typeId>
		<typeCh></typeCh>
		<classId>30</classId>
		<classCh>單一動詞[氣象景觀]</classCh>
		<classNo>5</classNo>
		<choiceOneOrder>2</choiceOneOrder>
		<choiceOneAAb>tam mavacangʉ a 'acangʉrahlʉ!</choiceOneAAb>
		<choiceOneACh>星星很美麗！</choiceOneACh>
		<choiceOneBAb>tam mavacangʉ a valahlʉvahlʉ!</choiceOneBAb>
		<choiceOneBCh>彩虹很美麗！</choiceOneBCh>
		<choiceOneCAb>tam mavacangʉ a vulahlʉ!</choiceOneCAb>
		<choiceOneCCh>月亮很美麗！</choiceOneCCh>
	</item>
	<item>
		<autoId>5071</autoId>
		<languageId>16</languageId>
		<languageCh></languageCh>
		<dialectId>37</dialectId>
		<dialectCh></dialectCh>
		<typeId>4</typeId>
		<typeCh></typeCh>
		<classId>30</classId>
		<classCh>單一動詞[氣象景觀]</classCh>
		<classNo>5</classNo>
		<choiceOneOrder>3</choiceOneOrder>
		<choiceOneAAb>murumita cu i vulahlʉ?</choiceOneAAb>
		<choiceOneACh>月亮出來了嗎？</choiceOneACh>
		<choiceOneBAb>murumita cu i 'acangʉrahlʉ?</choiceOneBAb>
		<choiceOneBCh>星星出來了嗎？</choiceOneBCh>
		<choiceOneCAb>murumita cu i tahliariia?</choiceOneCAb>
		<choiceOneCCh>太陽出來了嗎？</choiceOneCCh>
	</item>
	<item>
		<autoId>5070</autoId>
		<languageId>16</languageId>
		<languageCh></languageCh>
		<dialectId>37</dialectId>
		<dialectCh></dialectCh>
		<typeId>4</typeId>
		<typeCh></typeCh>
		<classId>30</classId>
		<classCh>單一動詞[氣象景觀]</classCh>
		<classNo>5</classNo>
		<choiceOneOrder>4</choiceOneOrder>
		<choiceOneAAb>tam mavacangʉ a valahlʉvahlʉ na kitaʉ!</choiceOneAAb>
		<choiceOneACh>彩虹看起來很美麗！</choiceOneACh>
		<choiceOneBAb>tam mavacahlʉ a vulahlʉ na kitaʉ!</choiceOneBAb>
		<choiceOneBCh>月亮看起來很美麗！</choiceOneBCh>
		<choiceOneCAb>tam mavacahlʉ a tahliariia na kitaʉ!</choiceOneCAb>
		<choiceOneCCh>太陽看起來很美麗！</choiceOneCCh>
	</item>
	<item>
		<autoId>5069</autoId>
		<languageId>16</languageId>
		<languageCh></languageCh>
		<dialectId>37</dialectId>
		<dialectCh></dialectCh>
		<typeId>4</typeId>
		<typeCh></typeCh>
		<classId>30</classId>
		<classCh>單一動詞[氣象景觀]</classCh>
		<classNo>5</classNo>
		<choiceOneOrder>5</choiceOneOrder>
		<choiceOneAAb>arinani ia mavacangʉ a langica!</choiceOneAAb>
		<choiceOneACh>今天是好天氣！</choiceOneACh>
		<choiceOneBAb>umusahli cu!</choiceOneBAb>
		<choiceOneBCh>下雨了！</choiceOneBCh>
		<choiceOneCAb>tam mavacangʉ a valahlʉvahlʉ!</choiceOneCAb>
		<choiceOneCCh>彩虹很美麗！</choiceOneCCh>
	</item>
</dataroot>