<?xml version='1.0' encoding='utf-8'?><dataroot><title>cekecekelrelri</title><titleCh>我的家庭</titleCh><item><text>talima nai ka cekecekelre.</text><chinese>我家有五個人。</chinese><wordChinese>有五 我們 虛詞 家庭</wordChinese><sound>true</sound><order>1</order></item><title>cekecekelrelri</title><titleCh>我的家庭</titleCh><item><text>kaingo, tama, tina, agilri#ka#ababay si konako.</text><chinese>祖母、父親、母親、妹妹、和我。</chinese><wordChinese>祖母 父親 母親 我的妹妹 虛詞 我自己</wordChinese><sound>true</sound><order>2</order></item><title>cekecekelrelri</title><titleCh>我的家庭</titleCh><item><text>aw takesikesi yako ki kosiyaw.</text><chinese>我讀國民小學。</chinese><wordChinese>虛詞 就讀 我 虛詞 國小</wordChinese><sound>true</sound><order>3</order></item><title>cekecekelrelri</title><titleCh>我的家庭</titleCh><item><text>ko agilri#ka#ababay takesikesi ki yoceyng.</text><chinese>我妹妹就讀幼稚園。</chinese><wordChinese>虛詞 我的妹妹 就讀 虛詞 幼稚園</wordChinese><sound>true</sound><order>4</order></item></dataroot>
