<?xml version='1.0' encoding='utf-8'?><dataroot><title>niciyo</title><titleCh>禮拜天</titleCh><item><text>ki eea ka sinci lra maka’iyalre ka vaiyana?</text><chinese>一個星期有幾天？</chinese><wordChinese>虛 一 虛 星期 虛 幾天 虛 今天</wordChinese><sound>true</sound><order>1</order></item><title>niciyo</title><titleCh>禮拜天</titleCh><item><text>ki eea ka sinci maka’itolro ka vaiyana.</text><chinese>一個星期有七天。</chinese><wordChinese>虛 一 虛 星期 七天 虛 今天</wordChinese><sound>true</sound><order>2</order></item><title>niciyo</title><titleCh>禮拜天</titleCh><item><text>lra sincici kai vaiyana?</text><chinese>今天是星期幾？</chinese><wordChinese>虛 星期 虛 今天</wordChinese><sound>true</sound><order>3</order></item><title>niciyo</title><titleCh>禮拜天</titleCh><item><text>niciyo kai vaiyana.</text><chinese>今天星期日。</chinese><wordChinese>星期日 虛 今天</wordChinese><sound>true</sound><order>4</order></item><title>niciyo</title><titleCh>禮拜天</titleCh><item><text>ywa ta kiyokai lihai.</text><chinese>我們要到教會禮拜。</chinese><wordChinese>去 我們 教會 禮拜</wordChinese><sound>true</sound><order>5</order></item></dataroot>
