<?xml version="1.0" encoding="utf-8"?><dataroot>
	<item>
		<autoId>1370</autoId>
		<languageId>2</languageId>
		<languageCh></languageCh>
		<dialectId>8</dialectId>
		<dialectCh></dialectCh>
		<typeId>5</typeId>
		<typeCh></typeCh>
		<classId>33</classId>
		<classCh>訊息問句[問地方]</classCh>
		<classNo>3</classNo>
		<choiceTwoOrder>1</choiceTwoOrder>
		<choiceTwoAAb>kiya inu' ku ungay su'?</choiceTwoAAb>
		<choiceTwoACh>你的猴子在哪裡？</choiceTwoACh>
		<choiceTwoBAb>kiya inu' ku ngiyaw su'?</choiceTwoBAb>
		<choiceTwoBCh>你的貓在哪裡？</choiceTwoBCh>
		<choiceTwoCAb>kiya inu' ku qwalit su'?</choiceTwoCAb>
		<choiceTwoCCh>你的老鼠在哪裡？</choiceTwoCCh>
	</item>
	<item>
		<autoId>1369</autoId>
		<languageId>2</languageId>
		<languageCh></languageCh>
		<dialectId>8</dialectId>
		<dialectCh></dialectCh>
		<typeId>5</typeId>
		<typeCh></typeCh>
		<classId>33</classId>
		<classCh>訊息問句[問地方]</classCh>
		<classNo>3</classNo>
		<choiceTwoOrder>2</choiceTwoOrder>
		<choiceTwoAAb>kiya inu' i yaki muw?</choiceTwoAAb>
		<choiceTwoACh>我祖母在哪裡？</choiceTwoACh>
		<choiceTwoBAb>kiya inu' i yaya muw?</choiceTwoBAb>
		<choiceTwoBCh>我媽媽在哪裡？</choiceTwoBCh>
		<choiceTwoCAb>kiya inu' i qumisuwan mu na kanayril?</choiceTwoCAb>
		<choiceTwoCCh>我姊姊在哪裡？</choiceTwoCCh>
	</item>
	<item>
		<autoId>1368</autoId>
		<languageId>2</languageId>
		<languageCh></languageCh>
		<dialectId>8</dialectId>
		<dialectCh></dialectCh>
		<typeId>5</typeId>
		<typeCh></typeCh>
		<classId>33</classId>
		<classCh>訊息問句[問地方]</classCh>
		<classNo>3</classNo>
		<choiceTwoOrder>3</choiceTwoOrder>
		<choiceTwoAAb>kiya inu' ku kanayril haca?</choiceTwoAAb>
		<choiceTwoACh>那個女人在哪裡？</choiceTwoACh>
		<choiceTwoBAb>kiya inu' ku sinsang haca?</choiceTwoBAb>
		<choiceTwoBCh>那個醫生在哪裡？</choiceTwoBCh>
		<choiceTwoCAb>kiya inu' ku sinsi' haca?</choiceTwoCAb>
		<choiceTwoCCh>那個老師在哪裡？</choiceTwoCCh>
	</item>
	<item>
		<autoId>1367</autoId>
		<languageId>2</languageId>
		<languageCh></languageCh>
		<dialectId>8</dialectId>
		<dialectCh></dialectCh>
		<typeId>5</typeId>
		<typeCh></typeCh>
		<classId>33</classId>
		<classCh>訊息問句[問地方]</classCh>
		<classNo>3</classNo>
		<choiceTwoOrder>4</choiceTwoOrder>
		<choiceTwoAAb>kiya inu' ku siyatu' ta'?</choiceTwoAAb>
		<choiceTwoACh>我們的衣服在哪裡？</choiceTwoACh>
		<choiceTwoBAb>kiya inu' ku pila' ta'?</choiceTwoBAb>
		<choiceTwoBCh>我們的錢在哪裡？</choiceTwoBCh>
		<choiceTwoCAb>kiya inu' ku tabakuy ta'?</choiceTwoCAb>
		<choiceTwoCCh>我們的雨傘在哪裡？</choiceTwoCCh>
	</item>
	<item>
		<autoId>1366</autoId>
		<languageId>2</languageId>
		<languageCh></languageCh>
		<dialectId>8</dialectId>
		<dialectCh></dialectCh>
		<typeId>5</typeId>
		<typeCh></typeCh>
		<classId>33</classId>
		<classCh>訊息問句[問地方]</classCh>
		<classNo>3</classNo>
		<choiceTwoOrder>5</choiceTwoOrder>
		<choiceTwoAAb>kiya inu' ku imuwag niya'?</choiceTwoAAb>
		<choiceTwoACh>她的家在哪裡？</choiceTwoACh>
		<choiceTwoBAb>kiya inu' ku papatiqan niya'?</choiceTwoBAb>
		<choiceTwoBCh>她的學校在哪裡？</choiceTwoBCh>
		<choiceTwoCAb>kiya inu' ku suwayi' niya' na kanayril?</choiceTwoCAb>
		<choiceTwoCCh>她的妹妹在哪裡？</choiceTwoCCh>
	</item>
</dataroot>