<?xml version="1.0" encoding="utf-8"?><dataroot>
	<item>
		<autoId>1548</autoId>
		<languageId>1</languageId>
		<languageCh></languageCh>
		<dialectId>3</dialectId>
		<dialectCh></dialectCh>
		<typeId>3</typeId>
		<typeCh></typeCh>
		<classId>21</classId>
		<classCh>訊息問句[問地方]</classCh>
		<classNo>2</classNo>
		<recognizeOrder>1</recognizeOrder>
		<recognizeAb>Icowa ko kolong ako?</recognizeAb>
		<recognizeCh>我的牛在哪裡？</recognizeCh>
		<recognizeNo></recognizeNo>
	</item>
	<item>
		<autoId>1549</autoId>
		<languageId>1</languageId>
		<languageCh></languageCh>
		<dialectId>3</dialectId>
		<dialectCh></dialectCh>
		<typeId>3</typeId>
		<typeCh></typeCh>
		<classId>21</classId>
		<classCh>訊息問句[問地方]</classCh>
		<classNo>2</classNo>
		<recognizeOrder>2</recognizeOrder>
		<recognizeAb>Icowa ko siri ako?</recognizeAb>
		<recognizeCh>我的羊在哪裡？</recognizeCh>
		<recognizeNo></recognizeNo>
	</item>
	<item>
		<autoId>1550</autoId>
		<languageId>1</languageId>
		<languageCh></languageCh>
		<dialectId>3</dialectId>
		<dialectCh></dialectCh>
		<typeId>3</typeId>
		<typeCh></typeCh>
		<classId>21</classId>
		<classCh>訊息問句[問地方]</classCh>
		<classNo>2</classNo>
		<recognizeOrder>3</recognizeOrder>
		<recognizeAb>Icowa ko ekong ako?</recognizeAb>
		<recognizeCh>我的貓頭鷹在哪裡？</recognizeCh>
		<recognizeNo></recognizeNo>
	</item>
	<item>
		<autoId>1551</autoId>
		<languageId>1</languageId>
		<languageCh></languageCh>
		<dialectId>3</dialectId>
		<dialectCh></dialectCh>
		<typeId>3</typeId>
		<typeCh></typeCh>
		<classId>21</classId>
		<classCh>訊息問句[問地方]</classCh>
		<classNo>2</classNo>
		<recognizeOrder>4</recognizeOrder>
		<recognizeAb>Icowa ko parad nangra?</recognizeAb>
		<recognizeCh>他們的桌子在哪裡？</recognizeCh>
		<recognizeNo></recognizeNo>
	</item>
	<item>
		<autoId>1552</autoId>
		<languageId>1</languageId>
		<languageCh></languageCh>
		<dialectId>3</dialectId>
		<dialectCh></dialectCh>
		<typeId>3</typeId>
		<typeCh></typeCh>
		<classId>21</classId>
		<classCh>訊息問句[問地方]</classCh>
		<classNo>2</classNo>
		<recognizeOrder>5</recognizeOrder>
		<recognizeAb>Icowa ko 'anengan nangra?</recognizeAb>
		<recognizeCh>他們的椅子在哪裡？</recognizeCh>
		<recognizeNo></recognizeNo>
	</item>
	<item>
		<autoId>1553</autoId>
		<languageId>1</languageId>
		<languageCh></languageCh>
		<dialectId>3</dialectId>
		<dialectCh></dialectCh>
		<typeId>3</typeId>
		<typeCh></typeCh>
		<classId>21</classId>
		<classCh>訊息問句[問地方]</classCh>
		<classNo>2</classNo>
		<recognizeOrder>6</recognizeOrder>
		<recognizeAb>Icowa ko tingnaw nangra?</recognizeAb>
		<recognizeCh>他們的電腦在哪裡？</recognizeCh>
		<recognizeNo></recognizeNo>
	</item>
	<item>
		<autoId>1554</autoId>
		<languageId>1</languageId>
		<languageCh></languageCh>
		<dialectId>3</dialectId>
		<dialectCh></dialectCh>
		<typeId>3</typeId>
		<typeCh></typeCh>
		<classId>21</classId>
		<classCh>訊息問句[問地方]</classCh>
		<classNo>2</classNo>
		<recognizeOrder>7</recognizeOrder>
		<recognizeAb>Icowa ko konga iso?</recognizeAb>
		<recognizeCh>你的地瓜在哪裡？</recognizeCh>
		<recognizeNo></recognizeNo>
	</item>
	<item>
		<autoId>1555</autoId>
		<languageId>1</languageId>
		<languageCh></languageCh>
		<dialectId>3</dialectId>
		<dialectCh></dialectCh>
		<typeId>3</typeId>
		<typeCh></typeCh>
		<classId>21</classId>
		<classCh>訊息問句[問地方]</classCh>
		<classNo>2</classNo>
		<recognizeOrder>8</recognizeOrder>
		<recognizeAb>Icowa ko 'ariray iso?</recognizeAb>
		<recognizeCh>你的玉米在哪裡？</recognizeCh>
		<recognizeNo></recognizeNo>
	</item>
	<item>
		<autoId>1556</autoId>
		<languageId>1</languageId>
		<languageCh></languageCh>
		<dialectId>3</dialectId>
		<dialectCh></dialectCh>
		<typeId>3</typeId>
		<typeCh></typeCh>
		<classId>21</classId>
		<classCh>訊息問句[問地方]</classCh>
		<classNo>2</classNo>
		<recognizeOrder>9</recognizeOrder>
		<recognizeAb>Icowa ko tamorak iso?</recognizeAb>
		<recognizeCh>你的南瓜在哪裡？</recognizeCh>
		<recognizeNo></recognizeNo>
	</item>
	<item>
		<autoId>1557</autoId>
		<languageId>1</languageId>
		<languageCh></languageCh>
		<dialectId>3</dialectId>
		<dialectCh></dialectCh>
		<typeId>3</typeId>
		<typeCh></typeCh>
		<classId>21</classId>
		<classCh>訊息問句[問地方]</classCh>
		<classNo>2</classNo>
		<recognizeOrder>10</recognizeOrder>
		<recognizeAb>Icowa ko pawli namo?</recognizeAb>
		<recognizeCh>你們的香蕉在哪裡？</recognizeCh>
		<recognizeNo></recognizeNo>
	</item>
	<item>
		<autoId>1558</autoId>
		<languageId>1</languageId>
		<languageCh></languageCh>
		<dialectId>3</dialectId>
		<dialectCh></dialectCh>
		<typeId>3</typeId>
		<typeCh></typeCh>
		<classId>21</classId>
		<classCh>訊息問句[問地方]</classCh>
		<classNo>2</classNo>
		<recognizeOrder>11</recognizeOrder>
		<recognizeAb>Icowa ko tefos namo?</recognizeAb>
		<recognizeCh>你們的甘蔗在哪裡？</recognizeCh>
		<recognizeNo></recognizeNo>
	</item>
	<item>
		<autoId>1559</autoId>
		<languageId>1</languageId>
		<languageCh></languageCh>
		<dialectId>3</dialectId>
		<dialectCh></dialectCh>
		<typeId>3</typeId>
		<typeCh></typeCh>
		<classId>21</classId>
		<classCh>訊息問句[問地方]</classCh>
		<classNo>2</classNo>
		<recognizeOrder>12</recognizeOrder>
		<recognizeAb>Icowa ko kiyafes namo?</recognizeAb>
		<recognizeCh>你們的番石榴在哪裡？</recognizeCh>
		<recognizeNo></recognizeNo>
	</item>
	<item>
		<autoId>1560</autoId>
		<languageId>1</languageId>
		<languageCh></languageCh>
		<dialectId>3</dialectId>
		<dialectCh></dialectCh>
		<typeId>3</typeId>
		<typeCh></typeCh>
		<classId>21</classId>
		<classCh>訊息問句[問地方]</classCh>
		<classNo>2</classNo>
		<recognizeOrder>13</recognizeOrder>
		<recognizeAb>Icowa ko loma' nira?</recognizeAb>
		<recognizeCh>她的家在哪裡？</recognizeCh>
		<recognizeNo></recognizeNo>
	</item>
	<item>
		<autoId>1561</autoId>
		<languageId>1</languageId>
		<languageCh></languageCh>
		<dialectId>3</dialectId>
		<dialectCh></dialectCh>
		<typeId>3</typeId>
		<typeCh></typeCh>
		<classId>21</classId>
		<classCh>訊息問句[問地方]</classCh>
		<classNo>2</classNo>
		<recognizeOrder>14</recognizeOrder>
		<recognizeAb>Icowa ko pitilidan nira?</recognizeAb>
		<recognizeCh>她的學校在哪裡？</recognizeCh>
		<recognizeNo></recognizeNo>
	</item>
	<item>
		<autoId>1562</autoId>
		<languageId>1</languageId>
		<languageCh></languageCh>
		<dialectId>3</dialectId>
		<dialectCh></dialectCh>
		<typeId>3</typeId>
		<typeCh></typeCh>
		<classId>21</classId>
		<classCh>訊息問句[問地方]</classCh>
		<classNo>2</classNo>
		<recognizeOrder>15</recognizeOrder>
		<recognizeAb>Icowa ko niyaro' nira?</recognizeAb>
		<recognizeCh>她的村莊在哪裡？</recognizeCh>
		<recognizeNo></recognizeNo>
	</item>
</dataroot>