<?xml version="1.0" encoding="utf-8"?><dataroot>
	<item>
		<autoId>806</autoId>
		<languageId>8</languageId>
		<languageCh></languageCh>
		<dialectId>30</dialectId>
		<dialectCh></dialectCh>
		<typeId>5</typeId>
		<typeCh></typeCh>
		<classId>31</classId>
		<classCh>訊息問句(問姓名、關係、數量、地方)</classCh>
		<classNo>1</classNo>
		<choiceTwoOrder>1</choiceTwoOrder>
		<choiceTwoAAb>manini acini ki kaka nyane?</choiceTwoAAb>
		<choiceTwoACh>他姊姊叫甚麼名字？</choiceTwoACh>
		<choiceTwoBAb>manini acini ki takawngo nyane?</choiceTwoBAb>
		<choiceTwoBCh>他祖母叫甚麼名字？</choiceTwoBCh>
		<choiceTwoCAb>manini acini ki titinyane?</choiceTwoCAb>
		<choiceTwoCCh>他媽媽叫甚麼名字？</choiceTwoCCh>
	</item>
	<item>
		<autoId>830</autoId>
		<languageId>8</languageId>
		<languageCh></languageCh>
		<dialectId>30</dialectId>
		<dialectCh></dialectCh>
		<typeId>5</typeId>
		<typeCh></typeCh>
		<classId>31</classId>
		<classCh>訊息問句(問姓名、關係、數量、地方)</classCh>
		<classNo>1</classNo>
		<choiceTwoOrder>2</choiceTwoOrder>
		<choiceTwoAAb>nanini kidroway maa'odrange?</choiceTwoAAb>
		<choiceTwoACh>那個老人是誰？</choiceTwoACh>
		<choiceTwoBAb>nanini kidroway sa'owalay?</choiceTwoBAb>
		<choiceTwoBCh>那個男人是誰？</choiceTwoBCh>
		<choiceTwoCAb>nanini kidroway valavalake?</choiceTwoCAb>
		<choiceTwoCCh>那個小孩是誰？</choiceTwoCCh>
	</item>
	<item>
		<autoId>829</autoId>
		<languageId>8</languageId>
		<languageCh></languageCh>
		<dialectId>30</dialectId>
		<dialectCh></dialectCh>
		<typeId>5</typeId>
		<typeCh></typeCh>
		<classId>31</classId>
		<classCh>訊息問句(問姓名、關係、數量、地方)</classCh>
		<classNo>1</classNo>
		<choiceTwoOrder>3</choiceTwoOrder>
		<choiceTwoAAb>kikay valavalake ka piyani nyane na bwathi?</choiceTwoAAb>
		<choiceTwoACh>這個小孩有幾個地瓜？</choiceTwoACh>
		<choiceTwoBAb>kikay valavalake ka piyani nyane na athiyoko?</choiceTwoBAb>
		<choiceTwoBCh>這個小孩有幾個橘子？</choiceTwoBCh>
		<choiceTwoCAb>kikay valavalake ka piyani nyane na belebele?</choiceTwoCAb>
		<choiceTwoCCh>這個小孩有幾根香蕉？</choiceTwoCCh>
	</item>
	<item>
		<autoId>828</autoId>
		<languageId>8</languageId>
		<languageCh></languageCh>
		<dialectId>30</dialectId>
		<dialectCh></dialectCh>
		<typeId>5</typeId>
		<typeCh></typeCh>
		<classId>31</classId>
		<classCh>訊息問句(問姓名、關係、數量、地方)</classCh>
		<classNo>1</classNo>
		<choiceTwoOrder>4</choiceTwoOrder>
		<choiceTwoAAb>watapiyaninga na caviliso?</choiceTwoAAb>
		<choiceTwoACh>你幾歲？</choiceTwoACh>
		<choiceTwoBAb>kaki mosoa ka watapiyaninga na cavilini?</choiceTwoBAb>
		<choiceTwoBCh>你哥哥幾歲？</choiceTwoBCh>
		<choiceTwoCAb>gili mosoa ka watapiyaninga na cavilini?</choiceTwoCAb>
		<choiceTwoCCh>你妹妹幾歲？</choiceTwoCCh>
	</item>
	<item>
		<autoId>827</autoId>
		<languageId>8</languageId>
		<languageCh></languageCh>
		<dialectId>30</dialectId>
		<dialectCh></dialectCh>
		<typeId>5</typeId>
		<typeCh></typeCh>
		<classId>31</classId>
		<classCh>訊息問句(問姓名、關係、數量、地方)</classCh>
		<classNo>1</classNo>
		<choiceTwoOrder>5</choiceTwoOrder>
		<choiceTwoAAb>'iyakayni ko kopingita?</choiceTwoAAb>
		<choiceTwoACh>我們的衣服在哪裡？</choiceTwoACh>
		<choiceTwoBAb>'iyakayni ko payswita?</choiceTwoBAb>
		<choiceTwoBCh>我們的錢在哪裡？</choiceTwoBCh>
		<choiceTwoCAb>'iyakayni ko kongokongita?</choiceTwoCAb>
		<choiceTwoCCh>我們的雨傘在哪裡？</choiceTwoCCh>
	</item>
</dataroot>