<?xml version="1.0" encoding="utf-8"?><dataroot>
	<item>
		<autoId>2583</autoId>
		<languageId>5</languageId>
		<languageCh></languageCh>
		<dialectId>17</dialectId>
		<dialectCh></dialectCh>
		<typeId>3</typeId>
		<typeCh></typeCh>
		<classId>20</classId>
		<classCh>擁有句</classCh>
		<classNo>1</classNo>
		<recognizeOrder>1</recognizeOrder>
		<recognizeAb>Niqan kingal ka huling mu.</recognizeAb>
		<recognizeCh>我有一隻狗。</recognizeCh>
		<recognizeNo></recognizeNo>
	</item>
	<item>
		<autoId>2584</autoId>
		<languageId>5</languageId>
		<languageCh></languageCh>
		<dialectId>17</dialectId>
		<dialectCh></dialectCh>
		<typeId>3</typeId>
		<typeCh></typeCh>
		<classId>20</classId>
		<classCh>擁有句</classCh>
		<classNo>1</classNo>
		<recognizeOrder>2</recognizeOrder>
		<recognizeAb>Niqan kingal ka ngiyaw mu.</recognizeAb>
		<recognizeCh>我有一隻貓。</recognizeCh>
		<recognizeNo></recognizeNo>
	</item>
	<item>
		<autoId>2585</autoId>
		<languageId>5</languageId>
		<languageCh></languageCh>
		<dialectId>17</dialectId>
		<dialectCh></dialectCh>
		<typeId>3</typeId>
		<typeCh></typeCh>
		<classId>20</classId>
		<classCh>擁有句</classCh>
		<classNo>1</classNo>
		<recognizeOrder>3</recognizeOrder>
		<recognizeAb>Niqan kingal ka qpatur mu.</recognizeAb>
		<recognizeCh>我有一隻青蛙。</recognizeCh>
		<recognizeNo></recognizeNo>
	</item>
	<item>
		<autoId>2586</autoId>
		<languageId>5</languageId>
		<languageCh></languageCh>
		<dialectId>17</dialectId>
		<dialectCh></dialectCh>
		<typeId>3</typeId>
		<typeCh></typeCh>
		<classId>20</classId>
		<classCh>擁有句</classCh>
		<classNo>1</classNo>
		<recognizeOrder>4</recognizeOrder>
		<recognizeAb>Niqan ka patas dha.</recognizeAb>
		<recognizeCh>他們有書。</recognizeCh>
		<recognizeNo></recognizeNo>
	</item>
	<item>
		<autoId>2587</autoId>
		<languageId>5</languageId>
		<languageCh></languageCh>
		<dialectId>17</dialectId>
		<dialectCh></dialectCh>
		<typeId>3</typeId>
		<typeCh></typeCh>
		<classId>20</classId>
		<classCh>擁有句</classCh>
		<classNo>1</classNo>
		<recognizeOrder>5</recognizeOrder>
		<recognizeAb>Niqan ka srus dha.</recognizeAb>
		<recognizeCh>他們有橡皮擦。</recognizeCh>
		<recognizeNo></recognizeNo>
	</item>
	<item>
		<autoId>2588</autoId>
		<languageId>5</languageId>
		<languageCh></languageCh>
		<dialectId>17</dialectId>
		<dialectCh></dialectCh>
		<typeId>3</typeId>
		<typeCh></typeCh>
		<classId>20</classId>
		<classCh>擁有句</classCh>
		<classNo>1</classNo>
		<recognizeOrder>6</recognizeOrder>
		<recognizeAb>Niqan ka  tuki dha.</recognizeAb>
		<recognizeCh>他們有鐘。</recognizeCh>
		<recognizeNo></recognizeNo>
	</item>
	<item>
		<autoId>2589</autoId>
		<languageId>5</languageId>
		<languageCh></languageCh>
		<dialectId>17</dialectId>
		<dialectCh></dialectCh>
		<typeId>3</typeId>
		<typeCh></typeCh>
		<classId>20</classId>
		<classCh>擁有句</classCh>
		<classNo>1</classNo>
		<recognizeOrder>7</recognizeOrder>
		<recognizeAb>Niqan ka  bunga su hug?</recognizeAb>
		<recognizeCh>你有地瓜嗎？</recognizeCh>
		<recognizeNo></recognizeNo>
	</item>
	<item>
		<autoId>2590</autoId>
		<languageId>5</languageId>
		<languageCh></languageCh>
		<dialectId>17</dialectId>
		<dialectCh></dialectCh>
		<typeId>3</typeId>
		<typeCh></typeCh>
		<classId>20</classId>
		<classCh>擁有句</classCh>
		<classNo>1</classNo>
		<recognizeOrder>8</recognizeOrder>
		<recognizeAb>Niqan ka sqmu su hug?</recognizeAb>
		<recognizeCh>你有玉米嗎？</recognizeCh>
		<recognizeNo></recognizeNo>
	</item>
	<item>
		<autoId>2591</autoId>
		<languageId>5</languageId>
		<languageCh></languageCh>
		<dialectId>17</dialectId>
		<dialectCh></dialectCh>
		<typeId>3</typeId>
		<typeCh></typeCh>
		<classId>20</classId>
		<classCh>擁有句</classCh>
		<classNo>1</classNo>
		<recognizeOrder>9</recognizeOrder>
		<recognizeAb>Niqan ka sari su hug?</recognizeAb>
		<recognizeCh>你有芋頭嗎？</recognizeCh>
		<recognizeNo></recognizeNo>
	</item>
	<item>
		<autoId>2592</autoId>
		<languageId>5</languageId>
		<languageCh></languageCh>
		<dialectId>17</dialectId>
		<dialectCh></dialectCh>
		<typeId>3</typeId>
		<typeCh></typeCh>
		<classId>20</classId>
		<classCh>擁有句</classCh>
		<classNo>1</classNo>
		<recognizeOrder>10</recognizeOrder>
		<recognizeAb>Niqan ka lukus nami.</recognizeAb>
		<recognizeCh>我們有衣服。</recognizeCh>
		<recognizeNo></recognizeNo>
	</item>
	<item>
		<autoId>2593</autoId>
		<languageId>5</languageId>
		<languageCh></languageCh>
		<dialectId>17</dialectId>
		<dialectCh></dialectCh>
		<typeId>3</typeId>
		<typeCh></typeCh>
		<classId>20</classId>
		<classCh>擁有句</classCh>
		<classNo>1</classNo>
		<recognizeOrder>11</recognizeOrder>
		<recognizeAb>Niqan ka bubung nami.</recognizeAb>
		<recognizeCh>我們有雨傘。</recognizeCh>
		<recognizeNo></recognizeNo>
	</item>
	<item>
		<autoId>2594</autoId>
		<languageId>5</languageId>
		<languageCh></languageCh>
		<dialectId>17</dialectId>
		<dialectCh></dialectCh>
		<typeId>3</typeId>
		<typeCh></typeCh>
		<classId>20</classId>
		<classCh>擁有句</classCh>
		<classNo>1</classNo>
		<recognizeOrder>12</recognizeOrder>
		<recognizeAb>Niqan ka bunuh / qbubu nami.</recognizeAb>
		<recognizeCh>我們有帽子。</recognizeCh>
		<recognizeNo></recognizeNo>
	</item>
	<item>
		<autoId>2595</autoId>
		<languageId>5</languageId>
		<languageCh></languageCh>
		<dialectId>17</dialectId>
		<dialectCh></dialectCh>
		<typeId>3</typeId>
		<typeCh></typeCh>
		<classId>20</classId>
		<classCh>擁有句</classCh>
		<classNo>1</classNo>
		<recognizeOrder>13</recognizeOrder>
		<recognizeAb>Niqan ka qbsuran na qrijil / kuyuh.</recognizeAb>
		<recognizeCh>她有姊姊。</recognizeCh>
		<recognizeNo></recognizeNo>
	</item>
	<item>
		<autoId>2596</autoId>
		<languageId>5</languageId>
		<languageCh></languageCh>
		<dialectId>17</dialectId>
		<dialectCh></dialectCh>
		<typeId>3</typeId>
		<typeCh></typeCh>
		<classId>20</classId>
		<classCh>擁有句</classCh>
		<classNo>1</classNo>
		<recognizeOrder>14</recognizeOrder>
		<recognizeAb>Niqan ka dangi / lupung na.</recognizeAb>
		<recognizeCh>她有朋友。</recognizeCh>
		<recognizeNo></recognizeNo>
	</item>
	<item>
		<autoId>2597</autoId>
		<languageId>5</languageId>
		<languageCh></languageCh>
		<dialectId>17</dialectId>
		<dialectCh></dialectCh>
		<typeId>3</typeId>
		<typeCh></typeCh>
		<classId>20</classId>
		<classCh>擁有句</classCh>
		<classNo>1</classNo>
		<recognizeOrder>15</recognizeOrder>
		<recognizeAb>Niqan ka swayi tama na.</recognizeAb>
		<recognizeCh>她有叔叔。</recognizeCh>
		<recognizeNo></recognizeNo>
	</item>
</dataroot>