<?xml version="1.0" encoding="utf-8"?><dataroot>
	<item>
		<autoId>4588</autoId>
		<languageId>5</languageId>
		<languageCh></languageCh>
		<dialectId>17</dialectId>
		<dialectCh></dialectCh>
		<typeId>4</typeId>
		<typeCh></typeCh>
		<classId>27</classId>
		<classCh>訊息問句[問地方]</classCh>
		<classNo>2</classNo>
		<choiceOneOrder>1</choiceOneOrder>
		<choiceOneAAb>Ga inu ka dapa / kacing mu?</choiceOneAAb>
		<choiceOneACh>我的牛在哪裡？</choiceOneACh>
		<choiceOneBAb>Ga inu ka miric(t) mu?</choiceOneBAb>
		<choiceOneBCh>我的羊在哪裡？</choiceOneBCh>
		<choiceOneCAb>Ga inu ka babuy su?</choiceOneCAb>
		<choiceOneCCh>我的豬在哪裡？</choiceOneCCh>
	</item>
	<item>
		<autoId>4587</autoId>
		<languageId>5</languageId>
		<languageCh></languageCh>
		<dialectId>17</dialectId>
		<dialectCh></dialectCh>
		<typeId>4</typeId>
		<typeCh></typeCh>
		<classId>27</classId>
		<classCh>訊息問句[問地方]</classCh>
		<classNo>2</classNo>
		<choiceOneOrder>2</choiceOneOrder>
		<choiceOneAAb>Ga inu ka ptasan dha?</choiceOneAAb>
		<choiceOneACh>他們的桌子在哪裡？</choiceOneACh>
		<choiceOneBAb>Ga inu ka tleengan dha?</choiceOneBAb>
		<choiceOneBCh>他們的椅子在哪裡？</choiceOneBCh>
		<choiceOneCAb>Ga inu lka qnawal dha?</choiceOneCAb>
		<choiceOneCCh>他們的電話在哪裡？</choiceOneCCh>
	</item>
	<item>
		<autoId>4586</autoId>
		<languageId>5</languageId>
		<languageCh></languageCh>
		<dialectId>17</dialectId>
		<dialectCh></dialectCh>
		<typeId>4</typeId>
		<typeCh></typeCh>
		<classId>27</classId>
		<classCh>訊息問句[問地方]</classCh>
		<classNo>2</classNo>
		<choiceOneOrder>3</choiceOneOrder>
		<choiceOneAAb>Ga inu ka phpah su?</choiceOneAAb>
		<choiceOneACh>你的花在哪裡？</choiceOneACh>
		<choiceOneBAb>Ga inu ka bunga su?</choiceOneBAb>
		<choiceOneBCh>你的地瓜在哪裡？</choiceOneBCh>
		<choiceOneCAb>Ga inu ka sqmu su?</choiceOneCAb>
		<choiceOneCCh>你的玉米在哪裡？</choiceOneCCh>
	</item>
	<item>
		<autoId>4585</autoId>
		<languageId>5</languageId>
		<languageCh></languageCh>
		<dialectId>17</dialectId>
		<dialectCh></dialectCh>
		<typeId>4</typeId>
		<typeCh></typeCh>
		<classId>27</classId>
		<classCh>訊息問句[問地方]</classCh>
		<classNo>2</classNo>
		<choiceOneOrder>4</choiceOneOrder>
		<choiceOneAAb>Ga inu ka blbul su?</choiceOneAAb>
		<choiceOneACh>你們的香蕉在哪裡？</choiceOneACh>
		<choiceOneBAb>Ga inu ka mudu / mami namu?</choiceOneBAb>
		<choiceOneBCh>你們的橘子在哪裡？</choiceOneBCh>
		<choiceOneCAb>Ga inu ka sibus namu?</choiceOneCAb>
		<choiceOneCCh>你們的甘蔗在哪裡？</choiceOneCCh>
	</item>
	<item>
		<autoId>4584</autoId>
		<languageId>5</languageId>
		<languageCh></languageCh>
		<dialectId>17</dialectId>
		<dialectCh></dialectCh>
		<typeId>4</typeId>
		<typeCh></typeCh>
		<classId>27</classId>
		<classCh>訊息問句[問地方]</classCh>
		<classNo>2</classNo>
		<choiceOneOrder>5</choiceOneOrder>
		<choiceOneAAb>Ga inu ka sapah na?</choiceOneAAb>
		<choiceOneACh>她的家在哪裡？</choiceOneACh>
		<choiceOneBAb>Ga inu ka sapah pyasan / ptasan na?</choiceOneBAb>
		<choiceOneBCh>她的學校在哪裡？</choiceOneBCh>
		<choiceOneCAb>Ga inu ka boru / qurug na?</choiceOneCAb>
		<choiceOneCCh>她的球在哪裡？</choiceOneCCh>
	</item>
</dataroot>