<?xml version='1.0' encoding='utf-8'?><dataroot><title>derun</title><titleCh>夏天</titleCh><item><text>ma’idang na danum i dinanumam nu derun,</text><chinese>夏天的溪水很大（流量充沛），</chinese><wordChinese>大的 虛詞 水 虛詞 溪水 虛詞 夏天</wordChinese><sound>true</sound><order>1</order></item><title>derun</title><titleCh>夏天</titleCh><item><text>makiteng mi kana derun harem.</text><chinese>冬天時的溪水很少（流量小）。</chinese><wordChinese>少的 虛詞 水 虛詞 溪水 虛詞 冬天</wordChinese><sound>true</sound><order>2</order></item><title>derun</title><titleCh>夏天</titleCh><item><text>katalawlepan mi kana derun harem.</text><chinese>我們現在是放暑假。</chinese><wordChinese>假日 我們 虛詞 夏天 現在/今天</wordChinese><sound>true</sound><order>3</order></item><title>derun</title><titleCh>夏天</titleCh><item><text>aymu, sadu a valiw.</text><chinese>可是，有很多颱風。</chinese><wordChinese>可是 很多的 虛詞 颱風</wordChinese><sound>true</sound><order>4</order></item></dataroot>
