<?xml version="1.0" encoding="utf-8"?><dataroot>
	<item>
		<autoId>2200</autoId>
		<languageId>12</languageId>
		<languageCh></languageCh>
		<dialectId>41</dialectId>
		<dialectCh></dialectCh>
		<typeId>5</typeId>
		<typeCh></typeCh>
		<classId>32</classId>
		<classCh>訊息問句[問數量]</classCh>
		<classNo>2</classNo>
		<choiceTwoOrder>1</choiceTwoOrder>
		<choiceTwoAAb>pidaya nannu takulris?</choiceTwoAAb>
		<choiceTwoACh>你有幾隻羊？</choiceTwoACh>
		<choiceTwoBAb>pidaya nannu vuyu?</choiceTwoBAb>
		<choiceTwoBCh>你有幾隻雞？</choiceTwoBCh>
		<choiceTwoCAb>pidaya nannu hulraw?</choiceTwoCAb>
		<choiceTwoCCh>你有幾隻魚？</choiceTwoCCh>
	</item>
	<item>
		<autoId>2199</autoId>
		<languageId>12</languageId>
		<languageCh></languageCh>
		<dialectId>41</dialectId>
		<dialectCh></dialectCh>
		<typeId>5</typeId>
		<typeCh></typeCh>
		<classId>32</classId>
		<classCh>訊息問句[問數量]</classCh>
		<classNo>2</classNo>
		<choiceTwoOrder>2</choiceTwoOrder>
		<choiceTwoAAb>pidaya nantu tu?</choiceTwoAAb>
		<choiceTwoACh>他有幾張桌子？</choiceTwoACh>
		<choiceTwoBAb>pidaya nantu lipad?</choiceTwoBAb>
		<choiceTwoBCh>他有幾張椅子？</choiceTwoBCh>
		<choiceTwoCAb>pidaya 'etiv nantu valray?</choiceTwoCAb>
		<choiceTwoCCh>他有幾本書？</choiceTwoCCh>
	</item>
	<item>
		<autoId>2198</autoId>
		<languageId>12</languageId>
		<languageCh></languageCh>
		<dialectId>41</dialectId>
		<dialectCh></dialectCh>
		<typeId>5</typeId>
		<typeCh></typeCh>
		<classId>32</classId>
		<classCh>訊息問句[問數量]</classCh>
		<classNo>2</classNo>
		<choiceTwoOrder>3</choiceTwoOrder>
		<choiceTwoAAb>pidaya tu vurasi ini na alrak?</choiceTwoAAb>
		<choiceTwoACh>這個小孩有幾個地瓜？</choiceTwoACh>
		<choiceTwoBAb>pidaya tu vartenuk ini na alrak?</choiceTwoBAb>
		<choiceTwoBCh>這個小孩有幾個橘子？</choiceTwoBCh>
		<choiceTwoCAb>pidaya tu velrvelr ini na alrak?</choiceTwoCAb>
		<choiceTwoCCh>這個小孩有幾根香蕉？</choiceTwoCCh>
	</item>
	<item>
		<autoId>2197</autoId>
		<languageId>12</languageId>
		<languageCh></languageCh>
		<dialectId>41</dialectId>
		<dialectCh></dialectCh>
		<typeId>5</typeId>
		<typeCh></typeCh>
		<classId>32</classId>
		<classCh>訊息問句[問數量]</classCh>
		<classNo>2</classNo>
		<choiceTwoOrder>4</choiceTwoOrder>
		<choiceTwoAAb>pidaya tu ruma' idu na vavayan?</choiceTwoAAb>
		<choiceTwoACh>那個女人有幾個房子？</choiceTwoACh>
		<choiceTwoBAb>pidaya tu suku idu na vavayan?</choiceTwoBAb>
		<choiceTwoBCh>那個女人有幾把雨傘？</choiceTwoBCh>
		<choiceTwoCAb>pidaya tu kavang idu na vavayan?</choiceTwoCAb>
		<choiceTwoCCh>那個女人有幾件衣服？</choiceTwoCCh>
	</item>
	<item>
		<autoId>2196</autoId>
		<languageId>12</languageId>
		<languageCh></languageCh>
		<dialectId>41</dialectId>
		<dialectCh></dialectCh>
		<typeId>5</typeId>
		<typeCh></typeCh>
		<classId>32</classId>
		<classCh>訊息問句[問數量]</classCh>
		<classNo>2</classNo>
		<choiceTwoOrder>5</choiceTwoOrder>
		<choiceTwoAAb>pidaya nu 'ami?</choiceTwoAAb>
		<choiceTwoACh>你幾歲？</choiceTwoACh>
		<choiceTwoBAb>pidaya tu 'ami ni vau na ma'inay?</choiceTwoBAb>
		<choiceTwoBCh>你哥哥幾歲？</choiceTwoBCh>
		<choiceTwoCAb>pidaya tu 'ami ni wadiyu na vavayan?</choiceTwoCAb>
		<choiceTwoCCh>你妹妹幾歲？</choiceTwoCCh>
	</item>
</dataroot>