<?xml version='1.0' encoding='utf-8'?><dataroot><title>ivokoli</title><titleCh>我的朋友</titleCh><item><text>madhaiae la’ivoko.</text><chinese>我有很多男性朋友。</chinese><wordChinese>多的 男性朋友（複數）</wordChinese><sound>true</sound><order>1</order></item><title>ivokoli</title><titleCh>我的朋友</titleCh><item><text>hiao ’a matoalrai hipono ’a masi’i.</text><chinese>hiao很高，hipono很矮。</chinese><wordChinese>（男名） （虛詞） 高的 （男名） （虛詞） 矮的</wordChinese><sound>true</sound><order>2</order></item><title>ivokoli</title><titleCh>我的朋友</titleCh><item><text>molrino ’a o’edhe’edheke, vedhao ’a malrakalrakase.</text><chinese>molrino很勤勞，vedhao很懶惰。</chinese><wordChinese>（女名） （虛詞） 勤勞的 （女名） （虛詞） 懶惰的</wordChinese><sound>true</sound><order>3</order></item><title>ivokoli</title><titleCh>我的朋友</titleCh><item><text>lo menanae ta’aelrenai ’ica’oca’o la ’osahiyo.</text><chinese>我們每天一起唸書玩耍。</chinese><wordChinese>（虛詞） 每天 一起 學習 （虛詞） 玩</wordChinese><sound>true</sound><order>4</order></item></dataroot>
